{
  "_как_редактировать": "downloadUrl — прямая ссылка на архив/модпак (например с Google Drive, MediaFire или CurseForge). version/modloader — просто текст-подпись. steps — шаги установки, каждый: title и text. Скопируй блок {...} для нового шага.",
  "version": "Сезон III — Whispers in the Void",
  "modloader": "Forge 1.20.1",
  "downloadUrl": "https://drive.google.com/file/d/151FaPHkHBwb0ivJpkCbUmUAQiTd-8y1T",
  "steps": [
    {
      "title": "Установи Forge",
      "text": "Скачай и установи Forge 1.20.1 с официального сайта, если ещё не стоит."
    },
    {
      "title": "Скачай сборку",
      "text": "Нажми кнопку выше, распакуй архив в папку .minecraft/mods (или как указано в архиве)."
    },
    {
      "title": "Заходи",
      "text": "Запусти игру с профилем Forge 1.20.1 и подключайся по IP с главной страницы."
    }
  ]
}
